fastapi_rich_logger/__init__.py
fastapi_rich_logger/middleware.py
mrd_studio_logger-0.1.0.dist-info/METADATA
mrd_studio_logger-0.1.0.dist-info/WHEEL
mrd_studio_logger-0.1.0.dist-info/top_level.txt
mrd_studio_logger-0.1.0.dist-info/RECORD
